nebu/__init__.py
nebu/auth.py
nebu/cache.py
nebu/config.py
nebu/data.py
nebu/errors.py
nebu/logging.py
nebu/meta.py
nebu/orign.py
nebu/builders/builder.py
nebu/builders/models.py
nebu/containers/container.py
nebu/containers/models.py
nebu/namespaces/models.py
nebu/namespaces/namespace.py
nebu/processors/consumer.py
nebu/processors/consumer_health_worker.py
nebu/processors/consumer_process_worker.py
nebu/processors/decorate.py
nebu/processors/default.py
nebu/processors/models.py
nebu/processors/processor.py
nebu/redis/models.py
nebu/services/service.py
nebu-0.1.132.dist-info/licenses/LICENSE
nebu-0.1.132.dist-info/WHEEL
nebu-0.1.132.dist-info/METADATA
nebu-0.1.132.dist-info/RECORD
