Metadata-Version: 2.4
Name: nebu
Version: 0.1.132
Summary: A globally distributed container runtime
Requires-Python: >=3.10.14
License-File: LICENSE
Requires-Dist: boto3>=1.37.30
Requires-Dist: dill>=0.3.8
Requires-Dist: loguru>=0.7.3
Requires-Dist: openai>=1.68.2
Requires-Dist: pillow>=10.4.0
Requires-Dist: pydantic>=2.10.6
Requires-Dist: pysocks>=1.7.1
Requires-Dist: pyyaml>=6.0.2
Requires-Dist: rclone-python>=0.1.21
Requires-Dist: redis>=5.0
Requires-Dist: requests>=2.32.3
